lenv/__init__.py
lenv/abc.py
lenv/config.py
lenv/errors.py
lenv/loader.py
lenv/metadata.py
lenv/types.py
lenv/validators.py
python_lenv-0.5.0.dist-info/METADATA
python_lenv-0.5.0.dist-info/WHEEL
python_lenv-0.5.0.dist-info/top_level.txt
python_lenv-0.5.0.dist-info/RECORD
