Metadata-Version: 2.1
Name: python-lenv
Version: 0.5.0
Summary: Quickly and efficiently load environment variables into a class
Home-page: https://github.com/pkeorley/python-lenv
Author: pkeorley
Author-email: pkeorley@gmail.com
License: MIT
Requires-Python: >=3.10
Requires-Dist: python-dotenv==1.0.1
